seamm_ase/__init__.py
seamm_ase/_version.py
seamm_ase/py.typed
seamm_ase/seamm_ase.py
seamm_ase/data/README.md
seamm_ase/data/look_and_say.dat
seamm_ase/data/references.bib
tests/__init__.py
tests/test_seamm_ase.py
seamm_ase-2025.2.7.dist-info/LICENSE.txt
seamm_ase-2025.2.7.dist-info/METADATA
seamm_ase-2025.2.7.dist-info/WHEEL
seamm_ase-2025.2.7.dist-info/top_level.txt
seamm_ase-2025.2.7.dist-info/RECORD
