Metadata-Version: 2.2
Name: seamm_ase
Version: 2025.2.7
Summary: Connector between SEAMM and ASE
Author-email: Paul Saxe <psaxe@vt.edu>
License: MIT
Project-URL: Source, https://github.com/molssi-seamm/seamm_ase/
Project-URL: Documentation, https://molssi-seamm.github.io/seamm_ase/
Classifier: License :: OSI Approved :: MIT License
Classifier: Programming Language :: Python :: 3
Requires-Python: >=3.8
License-File: LICENSE.txt
Requires-Dist: ase
Requires-Dist: bibtexparser
Requires-Dist: importlib-resources
Requires-Dist: numpy
Requires-Dist: seamm-util
Requires-Dist: tabulate
Provides-Extra: test
Requires-Dist: pytest>=6.1.2; extra == "test"
